omicidx_builder/__init__.py
omicidx_builder/bigquery_utils.py
omicidx_builder/biosample_kubernetes_job.py
omicidx_builder/cli.py
omicidx_builder/click_root.py
omicidx_builder/config.py
omicidx_builder/data/__init__.py
omicidx_builder/data/bigquery_schemas/__init__.py
omicidx_builder/data/bigquery_schemas/biosample.schema.json
omicidx_builder/data/bigquery_schemas/experiment.schema.json
omicidx_builder/data/bigquery_schemas/ontology_schema.json
omicidx_builder/data/bigquery_schemas/run.schema.json
omicidx_builder/data/bigquery_schemas/sample.schema.json
omicidx_builder/data/bigquery_schemas/sra_accession.schema.json
omicidx_builder/data/bigquery_schemas/study.schema.json
omicidx_builder/data/biosample_es_mapping.json
omicidx_builder/data/sra_es_mapping.json
omicidx_builder/elasticsearch_utils.py
omicidx_builder/gcs_utils.py
omicidx_builder/geo_cli.py
omicidx_builder/rdbms.py
omicidx_builder/sra_kubernetes_job.py
omicidx_builder/utils.py
omicidx_builder-0.5.1.dist-info/entry_points.txt
omicidx_builder-0.5.1.dist-info/WHEEL
omicidx_builder-0.5.1.dist-info/METADATA
omicidx_builder-0.5.1.dist-info/RECORD
