Metadata-Version: 2.1
Name: omicidx-builder
Version: 0.5.1
Summary: Tooling to build and deploy omicidx data and resources
Home-page: https://github.com/seandavi/omicidx-builder
License: MIT
Keywords: bioinformatics,genomics,metadata,omicidx,sequencing,NCBI
Author: Sean Davis
Author-email: seandavi@gmail.com
Requires-Python: >=3.7,<4.0
Classifier: Development Status :: 4 - Beta
Classifier: Environment :: Console
Classifier: Intended Audience :: Science/Research
Classifier: License :: OSI Approved :: MIT License
Classifier: Operating System :: OS Independent
Classifier: Programming Language :: Python :: 3
Classifier: Programming Language :: Python :: 3.7
Classifier: Programming Language :: Python :: 3.8
Classifier: Topic :: Database
Classifier: Topic :: Scientific/Engineering :: Bio-Informatics
Requires-Dist: Click
Requires-Dist: asyncpg (>=0.20.0,<0.21.0)
Requires-Dist: databases (>=0.2.6,<0.3.0)
Requires-Dist: elasticsearch (>=7,<8)
Requires-Dist: elasticsearch_dsl (>=7,<8)
Requires-Dist: google-cloud-bigquery
Requires-Dist: google-cloud-pubsub
Requires-Dist: google-cloud-storage
Requires-Dist: kubernetes (>=10.0.1,<11.0.0)
Requires-Dist: omicidx (==0.3.10)
Requires-Dist: psycopg2 (>=2.8,<3.0)
Requires-Dist: pydantic (>=1.1,<2.0)
Requires-Dist: sqlalchemy (>=1.3,<2.0)
Requires-Dist: toml (>=0.10,<0.11)
Requires-Dist: ujson (>=1.35,<2.0)
Project-URL: Repository, https://github.com/seandavi/omicidx-builder
